{
  "type": "tweet",
  "id": "1952747284678025368",
  "url": "https://x.com/cookmaster5000/status/1952747284678025368",
  "twitterUrl": "https://twitter.com/cookmaster5000/status/1952747284678025368",
  "text": "@Spectre__AI @bubblemaps Let’s get it",
  "source": "Twitter for iPhone",
  "retweetCount": 0,
  "replyCount": 0,
  "likeCount": 0,
  "quoteCount": 0,
  "viewCount": 0,
  "createdAt": "Tue Aug 05 15:03:27 +0000 2025",
  "lang": "en",
  "bookmarkCount": 0,
  "isReply": true,
  "inReplyToId": "1952746078312222951",
  "conversationId": "1952746078312222951",
  "inReplyToUserId": "1690423529643081728",
  "inReplyToUsername": "Spectre__AI",
  "author": {
    "type": "user",
    "userName": "cookmaster5000",
    "url": "https://x.com/cookmaster5000",
    "twitterUrl": "https://twitter.com/cookmaster5000",
    "id": "1755344978102898688",
    "name": "Grace",
    "isVerified": false,
    "isBlueVerified": false,
    "verifiedType": null,
    "profilePicture": "https://pbs.twimg.com/profile_images/1948056958201626625/LFRwgizL_normal.jpg",
    "coverPicture": "",
    "description": "",
    "location": "",
    "followers": 115,
    "following": 366,
    "status": "",
    "canDm": false,
    "canMediaTag": true,
    "createdAt": "Wed Feb 07 21:37:25 +0000 2024",
    "entities": {
      "description": {
        "urls": []
      },
      "url": {}
    },
    "fastFollowersCount": 0,
    "favouritesCount": 5808,
    "hasCustomTimelines": true,
    "isTranslator": false,
    "mediaCount": 1250,
    "statusesCount": 8978,
    "withheldInCountries": [],
    "affiliatesHighlightedLabel": {},
    "possiblySensitive": false,
    "pinnedTweetIds": [],
    "profile_bio": {
      "description": "",
      "entities": {
        "description": {}
      }
    },
    "isAutomated": false,
    "automatedBy": null
  },
  "extendedEntities": {},
  "card": null,
  "place": {},
  "entities": {
    "user_mentions": [
      {
        "id_str": "1690423529643081728",
        "indices": [
          0,
          12
        ],
        "name": "SPECTRE AI",
        "screen_name": "Spectre__AI"
      },
      {
        "id_str": "1385312402795859968",
        "indices": [
          13,
          24
        ],
        "name": "Bubblemaps",
        "screen_name": "bubblemaps"
      }
    ]
  },
  "quoted_tweet": null,
  "retweeted_tweet": null,
  "article": null
}