{
  "type": "tweet",
  "id": "1952747688727822548",
  "url": "https://x.com/thevalentinoasu/status/1952747688727822548",
  "twitterUrl": "https://twitter.com/thevalentinoasu/status/1952747688727822548",
  "text": "@CfcBilli @cysic_xyz @boundless_xyz This is actually Spot on bro ,ZK proofs are the bedrock of privacy &amp; scaling, but without  hardware, they’re stuck in the slow lane. @cysic_xyz accel stack + @boundless_xyz’s ecosystem = sub-second proof gen for rollups, private contracts &amp; verifiable AI. The future is ZK-fast!",
  "source": "Twitter for iPhone",
  "retweetCount": 0,
  "replyCount": 0,
  "likeCount": 0,
  "quoteCount": 0,
  "viewCount": 0,
  "createdAt": "Tue Aug 05 15:05:03 +0000 2025",
  "lang": "en",
  "bookmarkCount": 0,
  "isReply": true,
  "inReplyToId": "1952059352338387044",
  "conversationId": "1952059187069894947",
  "inReplyToUserId": "1853496307941289984",
  "inReplyToUsername": "CfcBilli",
  "author": {
    "type": "user",
    "userName": "thevalentinoasu",
    "url": "https://x.com/thevalentinoasu",
    "twitterUrl": "https://twitter.com/thevalentinoasu",
    "id": "1778881213098233856",
    "name": "VAL OF AFRICA 🌍 | 𝔽rAI",
    "isVerified": false,
    "isBlueVerified": false,
    "verifiedType": null,
    "profilePicture": "https://pbs.twimg.com/profile_images/1936087050786144256/xiHtT0-A_normal.jpg",
    "coverPicture": "https://pbs.twimg.com/profile_banners/1778881213098233856/1750434110",
    "description": "",
    "location": "",
    "followers": 375,
    "following": 1152,
    "status": "",
    "canDm": false,
    "canMediaTag": true,
    "createdAt": "Fri Apr 12 20:22:04 +0000 2024",
    "entities": {
      "description": {
        "urls": []
      },
      "url": {}
    },
    "fastFollowersCount": 0,
    "favouritesCount": 3719,
    "hasCustomTimelines": true,
    "isTranslator": false,
    "mediaCount": 384,
    "statusesCount": 5509,
    "withheldInCountries": [],
    "affiliatesHighlightedLabel": {},
    "possiblySensitive": false,
    "pinnedTweetIds": [
      "1844479293075882219"
    ],
    "profile_bio": {
      "description": "⏳A STORY UNTOLD📖 @themaitrixAI",
      "entities": {
        "description": {
          "user_mentions": [
            {
              "id_str": "0",
              "indices": [
                17,
                30
              ],
              "name": "",
              "screen_name": "themaitrixAI"
            }
          ]
        }
      }
    },
    "isAutomated": false,
    "automatedBy": null
  },
  "extendedEntities": {},
  "card": null,
  "place": {},
  "entities": {
    "user_mentions": [
      {
        "id_str": "1853496307941289984",
        "indices": [
          0,
          9
        ],
        "name": "CFCBilli🐐+",
        "screen_name": "CfcBilli"
      },
      {
        "id_str": "1539312810458370048",
        "indices": [
          10,
          20
        ],
        "name": "Cysic",
        "screen_name": "cysic_xyz"
      },
      {
        "id_str": "1828125622750646272",
        "indices": [
          21,
          35
        ],
        "name": "Boundless",
        "screen_name": "boundless_xyz"
      },
      {
        "id_str": "1539312810458370048",
        "indices": [
          173,
          183
        ],
        "name": "Cysic",
        "screen_name": "cysic_xyz"
      },
      {
        "id_str": "1828125622750646272",
        "indices": [
          198,
          212
        ],
        "name": "Boundless",
        "screen_name": "boundless_xyz"
      }
    ]
  },
  "quoted_tweet": null,
  "retweeted_tweet": null,
  "article": null
}