{
  "type": "tweet",
  "id": "1952747855375970396",
  "url": "https://x.com/gadlockhq/status/1952747855375970396",
  "twitterUrl": "https://twitter.com/gadlockhq/status/1952747855375970396",
  "text": "🤖 Chat with Gadlock AI\nSmart help, anytime\nGet instant answers, personalized support, and intelligent insights in chat.",
  "source": "Twitter for iPhone",
  "retweetCount": 0,
  "replyCount": 0,
  "likeCount": 0,
  "quoteCount": 0,
  "viewCount": 0,
  "createdAt": "Tue Aug 05 15:05:43 +0000 2025",
  "lang": "en",
  "bookmarkCount": 0,
  "isReply": true,
  "inReplyToId": "1952747851827548433",
  "conversationId": "1952747843774476515",
  "inReplyToUserId": "1930935101057110016",
  "inReplyToUsername": "gadlockhq",
  "author": {
    "type": "user",
    "userName": "gadlockhq",
    "url": "https://x.com/gadlockhq",
    "twitterUrl": "https://twitter.com/gadlockhq",
    "id": "1930935101057110016",
    "name": "Gadlock",
    "isVerified": false,
    "isBlueVerified": false,
    "verifiedType": null,
    "profilePicture": "https://pbs.twimg.com/profile_images/1930936065554075648/Go1EwhmL_normal.jpg",
    "coverPicture": "https://pbs.twimg.com/profile_banners/1930935101057110016/1749206957",
    "description": "",
    "location": "",
    "followers": 65,
    "following": 4,
    "status": "",
    "canDm": false,
    "canMediaTag": true,
    "createdAt": "Fri Jun 06 10:29:53 +0000 2025",
    "entities": {
      "description": {
        "urls": []
      },
      "url": {}
    },
    "fastFollowersCount": 0,
    "favouritesCount": 3,
    "hasCustomTimelines": true,
    "isTranslator": false,
    "mediaCount": 4,
    "statusesCount": 9,
    "withheldInCountries": [],
    "affiliatesHighlightedLabel": {},
    "possiblySensitive": false,
    "pinnedTweetIds": [
      "1938617482131976281"
    ],
    "profile_bio": {
      "description": "Person fit sell you stolen phone wey go land you for wahala.\nGadlock dey help you verify am.\n📲 Check before you buy!",
      "entities": {
        "description": {},
        "url": {
          "urls": [
            {
              "display_url": "gadlock.com",
              "expanded_url": "http://gadlock.com",
              "indices": [
                0,
                23
              ],
              "url": "https://t.co/EXSRP1lxZ9"
            }
          ]
        }
      }
    },
    "isAutomated": false,
    "automatedBy": null
  },
  "extendedEntities": {},
  "card": null,
  "place": {},
  "entities": {},
  "quoted_tweet": null,
  "retweeted_tweet": null,
  "article": null
}