{
  "type": "tweet",
  "id": "1952747851613651103",
  "url": "https://x.com/Noninfluente/status/1952747851613651103",
  "twitterUrl": "https://twitter.com/Noninfluente/status/1952747851613651103",
  "text": "@DaustoC 😂😂 l'ha detto un ragazzo ai suoi amici non io",
  "source": "Twitter for iPhone",
  "retweetCount": 0,
  "replyCount": 0,
  "likeCount": 0,
  "quoteCount": 0,
  "viewCount": 0,
  "createdAt": "Tue Aug 05 15:05:42 +0000 2025",
  "lang": "it",
  "bookmarkCount": 0,
  "isReply": true,
  "inReplyToId": "1952747512114160077",
  "conversationId": "1952740518774890951",
  "inReplyToUserId": "361403479",
  "inReplyToUsername": "DaustoC",
  "author": {
    "type": "user",
    "userName": "Noninfluente",
    "url": "https://x.com/Noninfluente",
    "twitterUrl": "https://twitter.com/Noninfluente",
    "id": "146738509",
    "name": "Enrico.",
    "isVerified": false,
    "isBlueVerified": false,
    "verifiedType": null,
    "profilePicture": "https://pbs.twimg.com/profile_images/1950262475779149825/hudLEyh8_normal.jpg",
    "coverPicture": "https://pbs.twimg.com/profile_banners/146738509/1422999522",
    "description": "",
    "location": "Pordenone",
    "followers": 21223,
    "following": 23280,
    "status": "",
    "canDm": true,
    "canMediaTag": true,
    "createdAt": "Sat May 22 06:10:53 +0000 2010",
    "entities": {
      "description": {
        "urls": []
      },
      "url": {}
    },
    "fastFollowersCount": 0,
    "favouritesCount": 298014,
    "hasCustomTimelines": true,
    "isTranslator": false,
    "mediaCount": 27614,
    "statusesCount": 743869,
    "withheldInCountries": [],
    "affiliatesHighlightedLabel": {},
    "possiblySensitive": false,
    "pinnedTweetIds": [],
    "profile_bio": {
      "description": "Sono il miglior sbaglio riuscito della società attuale, non c'è nulla da aggiungere.",
      "entities": {
        "description": {}
      }
    },
    "isAutomated": false,
    "automatedBy": null
  },
  "extendedEntities": {},
  "card": null,
  "place": {},
  "entities": {
    "user_mentions": [
      {
        "id_str": "361403479",
        "indices": [
          0,
          8
        ],
        "name": "Dausto 🍀🎗🏴‍☠️🏍️⛵️",
        "screen_name": "DaustoC"
      }
    ]
  },
  "quoted_tweet": null,
  "retweeted_tweet": null,
  "article": null
}